{
    "id": 1,
    "rubric": "Sabores de Morelos",
    "title": "La India Bonita: El Sabor de la Historia en Cuernavaca",
    "subtitle": "Un viaje sensorial donde cada sorbo cuenta siglos de historia y hospitalidad mexicana.",
    "por": "David Ochoa",
    "videoId": "",
    "featured": true,
    "tags": [
        "Mole Tradicional - $190",
        "Cecina con Chilaquiles - $210",
        "Desayuno Buffet - $250"
    ],
    "phoneNumber": "+52 777 333 0100",
    "facebookUrl": "https://www.facebook.com/indiabonita.restaurante/",
    "instagramUrl": "https://www.instagram.com/laindiabonitarestaurante/",
    "locationUrl": "https://www.google.com/maps/place/Restaurante+La+India+Bonita/@18.9231971,-99.2399843,17z/data=!3m1!4b1!4m6!3m5!1s0x85cdde4da2649e5d:0xd2a8dc66f2360811!8m2!3d18.923192!4d-99.237404!16s%2Fg%2F1vjdqdb6?entry=ttu&g_ep=EgoyMDI2MDIwMS4wIKXMDSoASAFQAw%3D%3D"
}